[
    {
        "id": 1,
        "question": "What is the total sale order value of this month?",
        "keywords": [
            "total","sale","order","value","this month"
        ],
        "insight": "The total sale order value of the month December is 8.99 lakhs."
    },
    {
        "id": 2,
        "question": "What is todays sale order value?",
        "keywords": [
            "sale","order","value","today"
        ],
        "insight": "The sale order value of today is 0."
    },
    {
        "id": 3,
        "question": "How many unregistered sale orders are there?",
        "keywords": [
            "unregistered","sale","order","count"
        ],
        "insight": "The count of unregistered sale orders for this financial year is 195."
    },
    {
        "id": 4,
        "question": "How many orders are waiting for packing?",
        "keywords": [
            "sale","order","waiting","packing","count"
        ],
        "insight": "The count of sale orders waiting for packing is 8."
    },
    {
        "id": 5,
        "question": "How many orders are waiting for Despatch?",
        "keywords": [
            "sale","order","waiting","despatch","count"
        ],
        "insight": "The count of sale orders waiting for despatch is 25."
    },
    {
        "id": 6,
        "question": "How many orders are waiting for invoice?",
        "keywords": [
            "sale","order","waiting","invoice","count"
        ],
        "insight": "The count of sale orders waiting for invoice is 7."
    },
    {
        "id": 7,
        "question": "How many orders are waiting for Reconciliation?",
        "keywords": [
            "sale","order","waiting","reconciliation","count"
        ],
        "insight": "The count of sale orders waiting for reconciliation is 21."
    },
    {
        "id": 8,
        "question": "Which week has the highest sale order value?",
        "keywords": [
            "week","highest","sale","order","value"
        ],
        "insight": "The week with the highest sale order value is week 21 with the amount value of 426 M."
    },
    {
        "id": 9,
        "question": "How many buyers are out of India buying from us?",
        "keywords": [
            "out","india","buying","country"
        ],
        "insight": "The count of buyers out of India buying from us is 7."
    },
    {
        "id": 10,
        "question": "Which is the top country that buys from us?",
        "keywords": [
            "top","country","buying","country","from"
        ],
        "insight": "The top country that buys from us is India with 56.1% of the total sale order value amounting to 345.01 Crores."
    },
    {
        "id": 11,
        "question": " who is the Top Buyer from us",
        "keywords": [
            "top","buyer","from","us"
        ],
        "insight": "The top buyer from us is Pillow Talk with 44.7% of the total sale order value amounting to 274.55 Crores."
    },
    {
        "id": 12,
        "question": "Who is the second top buyer from us",
        "keywords": [
            "second","top","buyer","from","us"
        ],
        "insight": "The second top buyer from us is TDL Textiles with 15.6% of the total sale order value amounting to 95.65 Crores."
    },
    {
        "id": 13,
        "question": "Who is the third top buyer from us",
        "keywords": [
            "third","top","buyer","from","us"
        ],
        "insight": "The third top buyer from us is Valmart Exports with 13.7% of the total sale order value amounting to 83.85 Crores."
    },
    {
        "id": 14,
        "question": "How many sale orders are from Export",
        "keywords": [
            "sale","order","export","count","summary"
        ],
        "insight": "There are 310 orders from export amoutning to 268.61 Crores."
    },
    {
        "id": 15,
        "question": " How many sale orders are from Local",
        "keywords": [
            "sale","order","local","count","summary"
        ],
        "insight": "There are 147 orders from local amoutning to 38.64 Crores."
    },
    {
        "id": 16,
        "question": " How many sale orders are from Interstate",
        "keywords": [
            "sale","order","interstate","count","summary"
        ],
        "insight": "There are 47 orders from interstate amoutning to 307.21 Crores."
    },
    {
        "id": 17,
        "question": " How many woven sale orders are there?",
        "keywords": [
            "sale","order","woven","count","summary"
        ],
        "insight": "There are 224 orders from woven amoutning to 263.74 Crores."
    },
    {
        "id": 18,
        "question": " How many Knitted sale orders are there?",
        "keywords": [
            "sale","order","knitted","count","summary"
        ],
        "insight": "There are 8 orders from knitted amoutning to 247 Crores."
    },
    {
        "id": 19,
        "question": " How many Sample sale order are there?",
        "keywords": [
            "sale","order","sample","count","summary"
        ],
        "insight": "There are 10 orders from sample amoutning to 1.34 Crores."
    },
    {
        "id": 20,
        "question": "How many Bulk sale order are there?",
        "keywords": [
            "sale","order","bulk","count","summary"
        ],
        "insight": "There are 494 orders from bulk amoutning to 613.12 Crores."
    },
    {
        "id": 21,
        "question": "How many overdue Shipments are there?",
        "keywords": [
            "overdue", "Shipments", "count", "summary"
        ],
        "insight": "There are 347 overdue shipments with quantity of 77 Lakh units and amounting to 615.72 Crores."
    },
    {
        "id": 22,
        "question": "How many scheduled shipments are there?",
        "keywords": [
            "scheduled", "shipments", "count", "summary"
        ],
        "insight": "There are 0 scheduled shipments with quantity of 0 units and amounting to 0 Rupees."
    },
    {
        "id": 23,
        "question": " How many completed Shipments are there?",
        "keywords": [
            "completed", "shipments", "count", "summary"
        ],
        "insight": "There are 36 completed shipments with 34 orders on time and 2 orders late."
    },
    {
        "id": 24,
        "question": "How many upcoming shipments are there?",
        "keywords": [
            "upcoming", "shipments", "count", "summary"
        ],
        "insight": "There are 3 upcoming shipments with quantity of 11 thousand units and amounting to 29.85 Lakhs."
    },
    {
        "id": 25,
        "question": "What is the total number of work orders in manufacturing?",
        "keywords": ["manufacturing", "work order", "total", "count"],
        "insight": "The total number of manufacturing work orders for this Financial Year is 321."
    },
    {
        "id": 26,
        "question": "How many manufacturing orders are currently running?",
        "keywords": ["manufacturing", "orders", "running", "count"],
        "insight": "There are 273 manufacturing orders currently in running status."
    },
    {
        "id": 27,
        "question": "How many manufacturing orders have been shipped?",
        "keywords": ["manufacturing", "orders", "shipped", "count"],
        "insight": "A total of 32 manufacturing orders have been shipped during the planning period."
    },
    {
        "id": 28,
        "question": "How many manufacturing orders are cancelled or unregistered?",
        "keywords": ["manufacturing", "orders", "cancelled", "unregistered", "count"],
        "insight": "There are 11 cancelled manufacturing orders and 5 unregistered manufacturing orders."
    },
    {
        "id": 29,
        "question": "How many orders are currently in Packing WIP status?",
        "keywords": ["packing", "WIP", "manufacturing", "orders", "count"],
        "insight": "There are 209 manufacturing orders currently in Work-In-Progress status at the Packing stage."
    },
    {
        "id": 30,
        "question": "How many manufacturing orders are critical across production stages?",
        "keywords": ["manufacturing", "critical", "orders", "summary"],
        "insight": "Critical orders are observed across multiple stages, including Packing (14), Final Packing Inspection (9), Cutting (3), Weaving (1), Yarn Dyeing (1), Purchase of Color Yarn (1), and Purchase of Greige Yarn (2)."
    },
    {
        "id": 31,
        "question": "Which manufacturing stage has the highest number of planned orders?",
        "keywords": ["manufacturing", "stage", "highest", "planned", "orders"],
        "insight": "The Work Order stage has the highest number of planned manufacturing orders with a total of 321 orders."
    },
    {
        "id": 32,
        "question": "What is the total stock value across all categories?",
        "keywords": ["stock", "total", "value", "summary"],
        "insight": "The total stock value across yarn, fabric, finished goods, accessories, packing material, and stores is 269.28 Crores."
    },
    {
        "id": 33,
        "question": "What is the total yarn stock value and current status?",
        "keywords": ["yarn", "stock", "value", "WIP", "inspection", "transit"],
        "insight": "The total yarn stock value is 250.73 Crores, consisting of 245.90 Crores stock in hand, 4.32 Crores in WIP, 44.98 Lakhs under inspection, and 6.34 Lakhs in transit."
    },
    {
        "id": 34,
        "question": "What is the total fabric stock value and its breakdown?",
        "keywords": ["fabric", "stock", "value", "breakdown"],
        "insight": "The total fabric stock value is 11.04 Crores, with 10.24 Crores stock in hand, 36.87 Lakhs in WIP, 42.87 Lakhs under inspection, and 68.82 Thousand in transit."
    },
    {
        "id": 35,
        "question": "What is the finished goods stock value?",
        "keywords": ["FG", "finished goods", "stock", "value"],
        "insight": "The total finished goods stock value is 2.68 Crores, including 2.51 Crores stock in hand and minor quantities in WIP and inspection."
    },
    {
        "id": 36,
        "question": "Which yarn product contributes the highest stock value?",
        "keywords": ["yarn", "product wise", "highest", "stock", "value"],
        "insight": "The yarn product 160DYP contributes the highest stock value with 690.57 units amounting to 250.52 Crores."
    },
    {
        "id": 37,
        "question": "Which yarn category holds the highest inventory value?",
        "keywords": ["yarn", "category wise", "highest", "inventory"],
        "insight": "The yarn category 160DYP holds the highest inventory value with 630.18 units amounting to 235.49 Crores."
    },
    {
        "id": 38,
        "question": "Which supplier contributes the highest yarn stock quantity?",
        "keywords": ["yarn", "supplier wise", "highest", "stock"],
        "insight": "The highest yarn stock quantity is tagged under 'No Supplier', contributing 9.28 Lakhs quantity amounting to 4.62 Crores, Based on the Quantity."
    },
    {
        "id": 39,
        "question": "What percentage of total stock value is contributed by yarn?",
        "keywords": ["yarn", "stock", "percentage", "total value"],
        "insight": "Yarn contributes approximately 93.7% of the total stock value, indicating that the majority of working capital is tied up in yarn inventory."
    },
    {
        "id": 40,
        "question": "How much stock value is currently blocked in WIP across all categories?",
        "keywords": ["stock", "WIP", "blocked", "value"],
        "insight": "The total stock value currently blocked in Work-In-Progress across yarn, fabric, finished goods, accessories, and packing material is approximately 4.82 Crores."
    },
    {
        "id": 41,
        "question": "How much stock is pending inspection across all categories?",
        "keywords": ["stock", "inspection pending", "value", "summary"],
        "insight": "Stock pending inspection amounts to approximately 90.51 Lakhs, primarily driven by yarn and fabric inventory awaiting quality clearance."
    },
    {
        "id": 42,
        "question": "Which warehouse holds the highest greige yarn quantity?",
        "keywords": ["warehouse wise", "yarn", "greige", "highest", "quantity"],
        "insight": "WS YARN WH 1 holds the highest greige yarn quantity with 20,983.258 kg valued at approximately 42.42 Lakhs."
    },
    {
        "id": 43,
        "question": "What is the split between colour yarn and greige yarn stock?",
        "keywords": ["yarn", "stage wise", "colour", "greige", "split"],
        "insight": "The yarn stock consists of approximately 9.62 Lakhs kg of colour yarn and 5.51 Lakhs kg of greige yarn, indicating a higher proportion of processed yarn."
    },
    {
        "id": 44,
        "question": "Which work order holds the highest yarn stock quantity?",
    "keywords": ["yarn", "workorder wise", "highest", "quantity"],
        "insight": "Work order Stock holds the highest yarn stock quantity at 5.17 Lakhs kg."
    },
    {
        "id": 45,
        "question": "How much yarn stock is not mapped to any supplier?",
        "keywords": ["yarn", "supplier wise", "no supplier", "risk"],
        "insight": "Approximately 9.28 Lakhs kg of yarn stock, valued at 4.62 Crores, is not mapped to any supplier, indicating a potential traceability and compliance risk."
    },
    {
        "id": 46,
        "question": "Which yarn certification category holds the highest stock quantity?",
        "keywords": ["yarn", "certification wise", "highest", "quantity"],
        "insight": "The ORGANIC certification category holds the highest yarn stock quantity, followed by -- yarn, indicating mixed compliance inventory."
    },
   {
        "id": 47,
        "question": "What is the total invoiced amount for shipped orders?",
        "keywords": ["MIS", "P&L", "total", "invoiced", "amount"],
        "insight": "The total invoiced amount for all shipped orders is 3.52 Crores With 25 Invoices"
    },
    {
        "id": 48,
        "question": "Who is the top buyer based on invoiced amount?",
        "keywords": ["top", "buyer", "invoiced", "amount", "MIS"],
        "insight": "ABC Traders is the top buyer based on invoiced amount, driven by multiple high-value shipped work orders."
    },
    {
        "id": 49,
        "question": "Who is the second top buyer based on invoiced amount?",
        "keywords": ["second", "top", "buyer", "invoiced", "amount"],
        "insight": "Valmart Exports is the second top buyer based on invoiced amount during the selected period."
    },
    {
        "id": 50,
        "question": "Which buyer has the lowest profit percentage?",
        "keywords": ["lowest", "profit", "percentage", "buyer", "MIS"],
        "insight": "Anglo French Textiles records the lowest profit percentage among shipped orders, indicating margin pressure on specific work orders."
    },
    {
        "id": 51,
        "question": "Which work order has the highest profit with stock?",
        "keywords": ["highest", "profit", "with stock", "work order"],
        "insight": "Multiple work orders from ABC Traders report the highest profit with stock at 100%, indicating zero expenses and full margin realization."
    },
    {
        "id": 52,
        "question": "Which work order has the lowest profit with stock percentage?",
        "keywords": ["lowest", "profit", "with stock", "percentage"],
        "insight": "The work order FABRIC-BLR from Anglo French Textiles shows the lowest profit with stock percentage at approximately 20.95%."
    },
    {
        "id": 53,
        "question": "What is the total profit with stock for all shipped orders?",
        "keywords": ["total", "profit", "with stock", "MIS", "summary"],
        "insight": "The total profit with stock is calculated as the aggregate of closing stock profit across all shipped work orders for the period."
    },
    {
        "id": 54,
        "question": "What is the total profit without stock for all shipped orders?",
        "keywords": ["total", "profit", "without stock", "MIS", "summary"],
        "insight": "The total profit without stock is amounting to 2.89 Crores when the Stock is included it amounts to 3.12 Crore with 25 Invoices"
    },
    {
        "id": 55,
        "question": "Which buyer has the highest average profit percentage?",
        "keywords": ["highest", "average", "profit", "percentage", "buyer"],
        "insight": "ABC Traders has the highest average profit percentage, consistently achieving near 100% margins across multiple shipped work orders."
    },
    {
        "id": 56,
        "question": "Are there any shipped orders with zero invoiced amount?",
        "keywords": ["zero", "invoiced", "amount", "shipped", "orders"],
        "insight": "Yes, the Sample Order from TDL Textiles has a shipped status but shows zero invoiced amount and zero profit."
    },
   {
        "id": 57,
        "question": "What are the top selling products by value?",
        "keywords": ["popular products", "top selling", "value", "sales"],
        "insight": "The top selling product by value is Cotton Knit Fabric with a sales value of 166.98 Crores, followed by Cotton Knit Fabric and Popplin Cotton Died Fbric."
    },
    {
        "id": 58,
        "question": "Which product has the highest sales quantity?",
        "keywords": ["product", "highest", "quantity", "sales"],
        "insight": "The product PLain Weave Fabrics has the highest sales quantity at 7.81 L units."
    },
    {
        "id": 59,
        "question": "What is the total sales value of top 10 popular products?",
        "keywords": ["top 10", "popular products", "total", "sales value"],
        "insight": "The combined sales value of the top popular products is driven primarily by high-volume fabric categories with 25.12L Quantity, totaling over 238.71 Crores."
    },
    {
        "id": 60,
        "question": "Which certification category contributes the highest sales value?",
        "keywords": ["certification wise", "highest", "sales value"],
        "insight": "The ORGANIC certification category contributes the highest sales value with a combined amount of 526.77 Crores."
    },
    {
        "id": 61,
        "question": "How many fabric and finished goods orders were placed?",
        "keywords": ["fabric", "FG", "orders", "count", "sales"],
        "insight": "There are 253 fabric orders amounting to 511.13 Crores and 252 finished goods orders amounting to 103.34 Crores."
    },
    {
        "id": 62,
        "question": "What is the split between buyer orders and stock orders?",
        "keywords": ["buyer", "stock", "orders", "split"],
        "insight": "Buyer orders account for 504 orders valued at 614.47 Crores, while there are no stock orders recorded for this period."
    }
]
